djcms_utils/__init__.py
djcms_utils/admin.py
djcms_utils/apps.py
djcms_utils/cms_plugins.py
djcms_utils/forms.py
djcms_utils/models.py
djcms_utils/tests.py
djcms_utils/views.py
djcms_utils/migrations/0001_initial.py
djcms_utils/migrations/0002_commondatapluginmodel.py
djcms_utils/migrations/__init__.py
djcms_utils/templates/admin/djcms_utils/plugins/plugin_change_form.html
iq_djangocms_utils-0.1.dist-info/METADATA
iq_djangocms_utils-0.1.dist-info/WHEEL
iq_djangocms_utils-0.1.dist-info/top_level.txt
iq_djangocms_utils-0.1.dist-info/RECORD
