Metadata-Version: 2.1
Name: iq-djangocms-utils
Version: 0.1
Summary: DjangoCMS-Utils - a Product by InQuant
Home-page: http://www.inquant.de
Author: Lutz Mende
Author-email: lutz.mende@inquant.de
License: GPL
Keywords: django utils helpers
Platform: UNKNOWN
